megapy/__init__.py
megapy/arduino.py
megapy/pin.py
megapy/pushbutton.py
megapy/stepper.py
megapy-0.0.7.dist-info/DESCRIPTION.rst
megapy-0.0.7.dist-info/METADATA
megapy-0.0.7.dist-info/RECORD
megapy-0.0.7.dist-info/WHEEL
megapy-0.0.7.dist-info/metadata.json
megapy-0.0.7.dist-info/top_level.txt
