Metadata-Version: 2.0
Name: megapy
Version: 0.0.7
Summary: A Python package to control Arduino Mega over USB Serial
Home-page: https://github.com/aakash-sahai/megapy
Author: Aakash Sahai
Author-email: sahaiaakash@gmail.com
License: UNKNOWN
Platform: UNKNOWN
Classifier: Programming Language :: Python :: 2
Classifier: License :: OSI Approved :: MIT License
Classifier: Operating System :: OS Independent
Requires-Dist: pyserial (>=3.0)
